admin_framework/__init__.py
admin_framework/apps.py
django_admin_framework-0.0.1.dist-info/LICENSE
django_admin_framework-0.0.1.dist-info/METADATA
django_admin_framework-0.0.1.dist-info/WHEEL
django_admin_framework-0.0.1.dist-info/top_level.txt
django_admin_framework-0.0.1.dist-info/zip-safe
django_admin_framework-0.0.1.dist-info/RECORD
